{"Shots on Goal":{"home":"6","away":"2"},"Shots off Goal":{"home":"8","away":"3"},"Total Shots":{"home":"20","away":"10"},"Blocked Shots":{"home":"6","away":"5"},"Shots insidebox":{"home":"15","away":"7"},"Shots outsidebox":{"home":"5","away":"3"},"Fouls":{"home":"11","away":"10"},"Corner Kicks":{"home":"3","away":"7"},"Offsides":{"home":"3","away":"1"},"Ball Possession":{"home":"51%","away":"49%"},"Yellow Cards":{"home":"3","away":"1"},"Red Cards":{"home":null,"away":null},"Goalkeeper Saves":{"home":"2","away":"7"},"Total passes":{"home":"395","away":"380"},"Passes accurate":{"home":"288","away":"271"},"Passes %":{"home":"73%","away":"71%"}}