{"Shots on Goal":{"home":"4","away":"6"},"Shots off Goal":{"home":"7","away":"3"},"Total Shots":{"home":"14","away":"9"},"Blocked Shots":{"home":"3","away":"0"},"Shots insidebox":{"home":"10","away":"7"},"Shots outsidebox":{"home":"4","away":"3"},"Fouls":{"home":"7","away":"19"},"Corner Kicks":{"home":"12","away":"9"},"Offsides":{"home":"0","away":"2"},"Ball Possession":{"home":"56%","away":"44%"},"Yellow Cards":{"home":"1","away":"3"},"Red Cards":{"home":null,"away":null},"Goalkeeper Saves":{"home":"4","away":"4"},"Total passes":{"home":"391","away":"306"},"Passes accurate":{"home":"304","away":"199"},"Passes %":{"home":"78%","away":"65%"}}