{"Shots on Goal":{"home":"7","away":"4"},"Shots off Goal":{"home":"11","away":"1"},"Total Shots":{"home":"21","away":"6"},"Blocked Shots":{"home":"3","away":"1"},"Shots insidebox":{"home":"13","away":"3"},"Shots outsidebox":{"home":"8","away":"3"},"Fouls":{"home":"12","away":"15"},"Corner Kicks":{"home":"3","away":"2"},"Offsides":{"home":"2","away":"3"},"Ball Possession":{"home":"55%","away":"45%"},"Yellow Cards":{"home":"0","away":"2"},"Red Cards":{"home":null,"away":null},"Goalkeeper Saves":{"home":"1","away":"6"},"Total passes":{"home":"474","away":"390"},"Passes accurate":{"home":"388","away":"296"},"Passes %":{"home":"82%","away":"76%"}}