{"Shots on Goal":{"home":"6","away":"4"},"Shots off Goal":{"home":"8","away":"4"},"Total Shots":{"home":"17","away":"11"},"Blocked Shots":{"home":"3","away":"3"},"Shots insidebox":{"home":"13","away":"4"},"Shots outsidebox":{"home":"5","away":"7"},"Fouls":{"home":"0","away":"0"},"Corner Kicks":{"home":"4","away":"3"},"Offsides":{"home":"6","away":"3"},"Ball Possession":{"home":"41%","away":"59%"},"Yellow Cards":{"home":"3","away":"1"},"Red Cards":{"home":null,"away":null},"Goalkeeper Saves":{"home":"3","away":"4"},"Total passes":{"home":"380","away":"542"},"Passes accurate":{"home":"287","away":"452"},"Passes %":{"home":"76%","away":"83%"}}