{"Shots on Goal":{"home":"5","away":"5"},"Shots off Goal":{"home":"6","away":"3"},"Total Shots":{"home":"11","away":"11"},"Blocked Shots":{"home":"0","away":"3"},"Shots insidebox":{"home":"6","away":"9"},"Shots outsidebox":{"home":"5","away":"2"},"Fouls":{"home":"12","away":"12"},"Corner Kicks":{"home":"5","away":"7"},"Offsides":{"home":"1","away":"2"},"Ball Possession":{"home":"43%","away":"57%"},"Yellow Cards":{"home":"2","away":"1"},"Red Cards":{"home":null,"away":null},"Goalkeeper Saves":{"home":"4","away":"3"},"Total passes":{"home":"370","away":"474"},"Passes accurate":{"home":"300","away":"389"},"Passes %":{"home":"81%","away":"82%"}}