{"Shots on Goal":{"home":"8","away":"9"},"Shots off Goal":{"home":"5","away":"3"},"Total Shots":{"home":"15","away":"17"},"Blocked Shots":{"home":"2","away":"5"},"Shots insidebox":{"home":"9","away":"11"},"Shots outsidebox":{"home":"7","away":"6"},"Fouls":{"home":"0","away":"0"},"Corner Kicks":{"home":"6","away":"1"},"Offsides":{"home":"3","away":"2"},"Ball Possession":{"home":"67%","away":"33%"},"Yellow Cards":{"home":"3","away":"2"},"Red Cards":{"home":null,"away":null},"Goalkeeper Saves":{"home":"7","away":"3"},"Total passes":{"home":"687","away":"326"},"Passes accurate":{"home":"619","away":"253"},"Passes %":{"home":"90%","away":"78%"}}