{"Shots on Goal":{"home":"4","away":"3"},"Shots off Goal":{"home":"6","away":"5"},"Total Shots":{"home":"17","away":"9"},"Blocked Shots":{"home":"7","away":"1"},"Shots insidebox":{"home":"9","away":"5"},"Shots outsidebox":{"home":"8","away":"4"},"Fouls":{"home":"0","away":"0"},"Corner Kicks":{"home":"5","away":"6"},"Offsides":{"home":"0","away":"1"},"Ball Possession":{"home":"52%","away":"48%"},"Yellow Cards":{"home":"0","away":"2"},"Red Cards":{"home":null,"away":null},"Goalkeeper Saves":{"home":"3","away":"0"},"Total passes":{"home":"490","away":"426"},"Passes accurate":{"home":"405","away":"330"},"Passes %":{"home":"83%","away":"77%"}}