{"Shots on Goal":{"home":"4","away":"1"},"Shots off Goal":{"home":"8","away":"6"},"Total Shots":{"home":"13","away":"12"},"Blocked Shots":{"home":"1","away":"5"},"Shots insidebox":{"home":"12","away":"5"},"Shots outsidebox":{"home":"1","away":"7"},"Fouls":{"home":"9","away":"10"},"Corner Kicks":{"home":"7","away":"7"},"Offsides":{"home":"4","away":"0"},"Ball Possession":{"home":"36%","away":"64%"},"Yellow Cards":{"home":"2","away":"2"},"Red Cards":{"home":null,"away":null},"Goalkeeper Saves":{"home":"1","away":"3"},"Total passes":{"home":"248","away":"448"},"Passes accurate":{"home":"149","away":"332"},"Passes %":{"home":"60%","away":"74%"}}